{
  "schemaVersion": 1,
  "name": "TEST canvas harvest fixture",
  "environmentAlias": "test",
  "solutionUniqueName": "TEST",
  "appDisplayName": "TEST",
  "browserProfileName": "test-canvas-harvest",
  "fixtureContainerName": "HarvestFixtureContainer",
  "defaultScreenDir": "fixtures/canvas-harvest/generated",
  "defaultScreenFiles": [
    "HarvestFixtureContainer.pa.yaml"
  ],
  "prototypeValidationScreenDir": "fixtures/canvas-harvest/generated/prototype-validation",
  "prototypeValidationScreenFiles": [
    "HarvestFixtureContainer.pa.yaml"
  ],
  "registryOut": "registries/canvas-controls.json",
  "catalogOut": "registries/canvas-control-catalog.json",
  "notes": [
    "Use this manifest as the canonical repo-local contract for the dedicated TEST harvest app and solution.",
    "The optional baseline reset zip remains environment-local; pass --reset-solution-zip explicitly for live refresh runs."
  ]
}
